[{"item_id": "T2_HEAD_CLOTH_SET1", "city": "5003", "quality": 2, "sell_price_min": 15, "sell_price_min_date": "2024-02-26T13:45:00", "sell_price_max": 16, "sell_price_max_date": "2024-02-26T13:45:00", "buy_price_min": 0, "buy_price_min_date": "0001-01-01T00:00:00", "buy_price_max": 0, "buy_price_max_date": "0001-01-01T00:00:00"}, {"item_id": "T2_HEAD_CLOTH_SET1", "city": "Black Market", "quality": 2, "sell_price_min": 0, "sell_price_min_date": "0001-01-01T00:00:00", "sell_price_max": 0, "sell_price_max_date": "0001-01-01T00:00:00", "buy_price_min": 115, "buy_price_min_date": "2024-02-26T14:00:00", "buy_price_max": 115, "buy_price_max_date": "2024-02-26T14:00:00"}, {"item_id": "T2_HEAD_CLOTH_SET1", "city": "Bridgewatch", "quality": 2, "sell_price_min": 68, "sell_price_min_date": "2024-02-26T16:40:00", "sell_price_max": 108, "sell_price_max_date": "2024-02-26T16:40:00", "buy_price_min": 0, "buy_price_min_date": "0001-01-01T00:00:00", "buy_price_max": 0, "buy_price_max_date": "0001-01-01T00:00:00"}, {"item_id": "T2_HEAD_CLOTH_SET1", "city": "Caerleon", "quality": 2, "sell_price_min": 996, "sell_price_min_date": "2024-02-26T17:10:00", "sell_price_max": 1000, "sell_price_max_date": "2024-02-26T17:10:00", "buy_price_min": 0, "buy_price_min_date": "0001-01-01T00:00:00", "buy_price_max": 0, "buy_price_max_date": "0001-01-01T00:00:00"}, {"item_id": "T2_HEAD_CLOTH_SET1", "city": "Fort Sterling", "quality": 2, "sell_price_min": 88, "sell_price_min_date": "2024-02-26T12:00:00", "sell_price_max": 101, "sell_price_max_date": "2024-02-26T12:00:00", "buy_price_min": 0, "buy_price_min_date": "0001-01-01T00:00:00", "buy_price_max": 0, "buy_price_max_date": "0001-01-01T00:00:00"}, {"item_id": "T2_HEAD_CLOTH_SET1", "city": "Lymhurst", "quality": 2, "sell_price_min": 69, "sell_price_min_date": "2024-02-26T15:15:00", "sell_price_max": 86, "sell_price_max_date": "2024-02-26T15:15:00", "buy_price_min": 0, "buy_price_min_date": "0001-01-01T00:00:00", "buy_price_max": 0, "buy_price_max_date": "0001-01-01T00:00:00"}, {"item_id": "T2_HEAD_CLOTH_SET1", "city": "Martlock", "quality": 2, "sell_price_min": 52, "sell_price_min_date": "2024-02-26T16:40:00", "sell_price_max": 85, "sell_price_max_date": "2024-02-26T16:40:00", "buy_price_min": 0, "buy_price_min_date": "0001-01-01T00:00:00", "buy_price_max": 0, "buy_price_max_date": "0001-01-01T00:00:00"}, {"item_id": "T2_HEAD_CLOTH_SET1", "city": "Swamp Cross", "quality": 2, "sell_price_min": 26, "sell_price_min_date": "2024-02-26T16:00:00", "sell_price_max": 26, "sell_price_max_date": "2024-02-26T16:00:00", "buy_price_min": 0, "buy_price_min_date": "0001-01-01T00:00:00", "buy_price_max": 0, "buy_price_max_date": "0001-01-01T00:00:00"}, {"item_id": "T2_HEAD_CLOTH_SET1", "city": "Thetford", "quality": 2, "sell_price_min": 30, "sell_price_min_date": "2024-02-26T16:00:00", "sell_price_max": 34, "sell_price_max_date": "2024-02-26T16:00:00", "buy_price_min": 0, "buy_price_min_date": "0001-01-01T00:00:00", "buy_price_max": 0, "buy_price_max_date": "0001-01-01T00:00:00"}]